jarvais/__init__.py
jarvais/analyzer/__init__.py
jarvais/analyzer/_utils.py
jarvais/analyzer/analyzer.py
jarvais/analyzer/settings.py
jarvais/analyzer/modules/__init__.py
jarvais/analyzer/modules/base.py
jarvais/analyzer/modules/cleaning.py
jarvais/analyzer/modules/dashboard.py
jarvais/analyzer/modules/encoding.py
jarvais/analyzer/modules/missingness.py
jarvais/analyzer/modules/outlier.py
jarvais/analyzer/modules/visualization.py
jarvais/cli/__init__.py
jarvais/cli/__main__.py
jarvais/cli/analyzer.py
jarvais/explainer/__init__.py
jarvais/explainer/bias.py
jarvais/explainer/explainer.py
jarvais/loggers/__init__.py
jarvais/loggers/logging_config.py
jarvais/loggers/processors.py
jarvais/trainer/__init__.py
jarvais/trainer/settings.py
jarvais/trainer/trainer.py
jarvais/trainer/modules/__init__.py
jarvais/trainer/modules/_leaderboard.py
jarvais/trainer/modules/_simple_regression_model.py
jarvais/trainer/modules/autogluon_trainer.py
jarvais/trainer/modules/feature_reduction.py
jarvais/trainer/modules/survival_trainer.py
jarvais/trainer/modules/deep_survival/__init__.py
jarvais/trainer/modules/deep_survival/deepsurv/__init__.py
jarvais/trainer/modules/deep_survival/deepsurv/deepsurv.py
jarvais/trainer/modules/deep_survival/deepsurv/train.py
jarvais/trainer/modules/deep_survival/deepsurv/utils.py
jarvais/trainer/modules/deep_survival/torchmtlr/__init__.py
jarvais/trainer/modules/deep_survival/torchmtlr/mtlr.py
jarvais/trainer/modules/deep_survival/torchmtlr/train.py
jarvais/trainer/modules/deep_survival/torchmtlr/utils.py
jarvais/utils/__init__.py
jarvais/utils/_design.py
jarvais/utils/_elements_analyzer.py
jarvais/utils/_plot_epic.py
jarvais/utils/functional.py
jarvais/utils/pdf.py
jarvais/utils/plot.py
jarvais/utils/statistical_ranking.py
jarvais/utils/features/__init__.py
jarvais/utils/features/constants.py
jarvais/utils/features/engineering.py
jarvais/utils/fonts/Inter_28pt-Bold.ttf
jarvais/utils/fonts/Inter_28pt-Regular.ttf
jarvais-0.20.0.dist-info/METADATA
jarvais-0.20.0.dist-info/WHEEL
jarvais-0.20.0.dist-info/entry_points.txt
jarvais-0.20.0.dist-info/licenses/LICENSE
jarvais-0.20.0.dist-info/RECORD
