Metadata-Version: 2.4
Name: jarvais
Version: 0.20.0
Summary: jarvAIs: just a really versatile AI service
Project-URL: Homepage, https://github.com/pmcdi/jarvais/
Project-URL: Source, https://github.com/pmcdi/jarvais/
Project-URL: Documentation, https://pmcdi.github.io/jarvais/
Author-email: Joshua Siraj <joshua.siraj@uhn.ca>, Sejin Kim <hello@sejin.kim>
License-Expression: MIT
License-File: LICENSE
Classifier: License :: OSI Approved :: MIT License
Classifier: Natural Language :: English
Classifier: Operating System :: OS Independent
Classifier: Programming Language :: Python :: 3.10
Classifier: Programming Language :: Python :: 3.11
Classifier: Programming Language :: Python :: 3.12
Requires-Python: <3.13,>=3.10
Requires-Dist: autogluon-tabular[all]>1.0
Requires-Dist: borb<3,>=2.1.25
Requires-Dist: click<9,>=8.2.1
Requires-Dist: fairlearn<0.13,>=0.12.0
Requires-Dist: fpdf2<3,>=2.8.1
Requires-Dist: htmlmin==0.1.12
Requires-Dist: lifelines<0.31,>=0.30.0
Requires-Dist: lightning<3,>=2.4.0
Requires-Dist: mrmr-selection==0.2.8
Requires-Dist: openpyxl<3.2,>=3.1.5
Requires-Dist: optuna-integration[pytorch-lightning]==4.1.0
Requires-Dist: optuna==4.1.0
Requires-Dist: pandas>2.0
Requires-Dist: prettytable<4,>=3.12.0
Requires-Dist: pydantic<3,>=2.11.3
Requires-Dist: pyyaml<7,>=6.0.2
Requires-Dist: rich<15,>=13.9.4
Requires-Dist: scikit-learn<2,>=1.5.2
Requires-Dist: scikit-survival<0.24,>=0.23.1
Requires-Dist: scipy<1.13,>=1.11.4
Requires-Dist: seaborn<0.14,>=0.13.2
Requires-Dist: shap<0.47,>=0.46.0
Requires-Dist: statsmodels<0.15,>=0.14.4
Requires-Dist: structlog<26,>=25.3.0
Requires-Dist: tableone==0.9.1
Requires-Dist: umap-learn<0.6,>=0.5.6
